slrfield/__init__.py
slrfield/cpf/__init__.py
slrfield/cpf/cpf_download.py
slrfield/cpf/cpf_interpolate.py
slrfield/cpf/cpf_read.py
slrfield/slrclasses/__init__.py
slrfield/slrclasses/cpfclass.py
slrfield/utils/__init__.py
slrfield/utils/data_download.py
slrfield/utils/data_prepare.py
slrfield/utils/try_download.py
slrfield-0.2.1.dist-info/LICENSE
slrfield-0.2.1.dist-info/METADATA
slrfield-0.2.1.dist-info/WHEEL
slrfield-0.2.1.dist-info/top_level.txt
slrfield-0.2.1.dist-info/RECORD
