Metadata-Version: 2.1
Name: slrfield
Version: 0.2.1
Summary: A package to handle the SLR(Satellite Laser Ranging) data
Home-page: https://github.com/lcx366/SLRfield
Author: Chunxiao Li
Author-email: lcx366@126.com
License: MIT
Keywords: SLR,CPF
Classifier: Development Status :: 4 - Beta
Classifier: Intended Audience :: Education
Classifier: Intended Audience :: Science/Research
Classifier: Programming Language :: Python :: 3.8
Classifier: Programming Language :: Python :: 3.9
Classifier: License :: OSI Approved :: MIT License
Requires-Python: >=3.8
License-File: LICENSE
Requires-Dist: scipy
Requires-Dist: numpy (>=1.21.2)
Requires-Dist: astropy (>=4.3.1)
Requires-Dist: wget
Requires-Dist: beautifulsoup4
